puppet/__init__.py
puppet/__main__.py
puppet/coco.py
puppet/cocohub_vendor.py
puppet/server.py
puppet/shell.py
puppet/state.py
puppet/templates.py
puppet/channels/__init__.py
puppet/channels/discord.py
puppet/channels/msbf.py
puppet/channels/telegram.py
puppet/func/__init__.py
puppet/nlu/__init__.py
puppet/nlu/regex.py
puppet/nlu/word_regex.py
puppet/std/__init__.py
puppet/std/eliza.py
coco_puppet-0.4.3.dist-info/LICENSE
coco_puppet-0.4.3.dist-info/METADATA
coco_puppet-0.4.3.dist-info/WHEEL
coco_puppet-0.4.3.dist-info/top_level.txt
coco_puppet-0.4.3.dist-info/RECORD
